Workbook

Sheet PT320_Materialidade
A1: PT 320 - Materialidade (NBC TA 320) - ALLOS S.A. consolidado 31/12/2025
A2: Preparador: matrícula 231004987 | Data: 20/10/2026 | Revisão: ____________ (campo reservado; sem assinatura simulada) | Valores em R$ mil, salvo indicação
A4: Base de referência (DFP 2025, consolidado) | B4: Valor (R$ mil) | C4: % usado | D4: Resultado (R$ mil) | E4: Fonte / justificativa
A5: Lucro antes dos impostos e contribuições (LAIR) | B5: 1017601 | C5: 0.05 | D5: =B5*C5 -> 50880.05 | E5: DFP 2025, DRE (PDF p.17; pág. 8 das DFs). Base ESCOLHIDA: medida de resultado estável, 5% (faixa usual 5%).
A6: Receita líquida de aluguel e serviços | B6: 2859106 | C6: 0.01 | D6: =B6*C6 -> 28591.06 | E6: DFP 2025, DRE. Alternativa (1% da receita), apenas comparação.
A7: Total do ativo | B7: 26006439 | C7: 0.005 | D7: =B7*C7 -> 130032.2 | E7: DFP 2025, balanço. Alternativa (0,5% do ativo), apenas comparação.
A8: Patrimônio líquido | B8: 13899006 | C8: 0.01 | D8: =B8*C8 -> 138990.06 | E8: DFP 2025, balanço. Alternativa (1% do PL), apenas comparação.
A10: MATERIALIDADE GLOBAL (escolhida = LAIR x 5%) | D10: =D5 -> 50880.05
A11: % da materialidade para execução (ME) | C11: 0.75 | D11: =D10*C11 -> 38160.037 | E11: 75%: risco inerente alto (estimativas de valor recuperável) e ambiente sem histórico de auditoria no trabalho (didático).
A12: Limite de distorções claramente triviais (5% da global) | C12: 0.05 | D12: =D10*C12 -> 2544.0025
A14: Materialidade específica 1 - Remuneração da administração/partes relacionadas (se aplicável) | E14: PLANEJADO: depende de dado interno; usar 10% do saldo/ transação da nota 23 (saldos de partes relacionadas R$ 55.865 ativo / 7.361 passivo).
A15: Materialidade específica 2 - Propriedades para investimento (saldo mais relevante) | B15: 20381666 | C15: 0.0025 | D15: =B15*C15 -> 50954.165 | E15: 0,25% do saldo; exibida para confronto com a ME (resulta em valor maior que a global: NÃO adotada; prevalece a global).
A17: Revisão da materialidade no curso do trabalho | E17: Sem informação nova que a altere. Se distorções quantificadas > global (ver PT450), reavaliar ME e ampliar testes.
A19: Em R$ (unidade da base simulada) | B19: =D10*1000 -> 50880050 | C19: =D11*1000 -> 38160038 | D19: =D12*1000 -> 2544002.5 | E19: B = global | C = execução | D = trivial

Sheet PT500_Conciliacao
A1: PT 500 - Conciliação da base simulada com o saldo contábil (nota 11) - DADOS SINTÉTICOS x DFP REAL
A2: Preparador: matrícula 231004987 | Data: 20/10/2026 | Revisão: ____________ (campo reservado; sem assinatura simulada) | Valores em R$ mil, salvo indicação
A4: Item | B4: R$ | C4: Observação
A5: Custo (nota 11, consolidado, R$ mil) | B5: 10800757 | C5: REAL - DFP 2025, PDF p.66
A6: (-) Depreciação acumulada (R$ mil) | B6: -2711228 | C6: REAL
A7: (+) Mais-valia líquida (R$ mil) | B7: 12292137 | C7: REAL
A8: Saldo contábil - Propriedades para investimento (R$ mil) | B8: =SUM(B5:B7) -> 20381666
A9: Saldo no balanço consolidado 31/12/2025 (R$ mil) | B9: 20381666 | C9: REAL - balanço, PDF p.15 (pág.6 das DFs)
A10: Diferença nota 11 x balanço (deve ser zero) | B10: =B8-B9 -> 0
A12: Base SIMULADA - soma do valor contábil líquido (R$) | B12: 2.0448165e+10 | C12: SINTÉTICO - script 02 (520.150 linhas)
A13: Saldo DFP em R$ | B13: =B9*1000 -> 20381666000
A14: Diferença base x saldo DFP (R$) | B14: =B12-B13 -> 66498980
A16: Explicação da diferença: erros inseridos (efeito no total da base) | B16: R$ | C16: Registro: dados/registro_erros_inseridos.csv
A17: DUPLICIDADE | B17: 22927175 | C17: 150 registros
A18: CORTE (ATIVACAO EM 2026) | B18: 0 | C18: 120 registros
A19: DEPRECIACAO INCORRETA | B19: 5410.58 | C19: 200 registros
A20: BAIXADO COM SALDO | B20: 0 | C20: 80 registros
A21: VCL NEGATIVO | B21: -18492927 | C21: 60 registros
A22: TERRENO DEPRECIADO | B22: -23071.29 | C22: 40 registros
A23: SEM DOCUMENTO SUPORTE | B23: 0 | C23: 300 registros
A24: LANCAMENTO MANUAL ATIPICO | B24: 62082392 | C24: 90 registros
A25: Soma dos efeitos dos erros inseridos | B25: =SUM(B17:B24) -> 66498980
A26: RESÍDUO NÃO EXPLICADO (arredondamento de centavos) | B26: =B14-B25 -> 0.049999386 | C26: Base limpa (antes dos erros) = saldo DFP exato; resíduo decorre de arredondamento em ponto flutuante ao gravar centavos.
A29: Roll-forward REAL do saldo (nota 11, R$ mil) | B29: R$ mil | C29: Fonte
A30: Saldo em 31/12/2024 | B30: 20700140 | C30: DFP 2025 nota 11 (PDF p.65)
A31: Adições: instalações e edificações (líq. depreciação) | B31: -91304 | C31: nota 11
A32: Adições: direito de uso | B32: -5576 | C32: nota 11
A33: Aquisição do Shopping Brasília | B33: 176577 | C33: nota 11
A34: Outros | B34: 4164 | C34: nota 11
A35: Baixa: 9,9% Plaza Sul | B35: -53881 | C35: nota 11
A36: Baixa: 45% Rio Anil | B36: -136703 | C36: nota 11
A37: Baixa: 10% Tijuca | B37: -150117 | C37: nota 11
A38: Baixa: 20% Carioca | B38: -61634 | C38: nota 11
A39: Saldo recalculado em 31/12/2025 | B39: =SUM(B30:B38) -> 20381666
A40: Diferença para o balanço (deve ser zero) | B40: =B39-B9 -> 0

Sheet PT530_Amostragem
A1: PT 530 - Amostragem MUS sobre a BASE SIMULADA (propriedades para investimento)
A2: Preparador: matrícula 231004987 | Data: 20/10/2026 | Revisão: ____________ (campo reservado; sem assinatura simulada) | Valores em R$ mil, salvo indicação
A4: Parâmetro | B4: Valor | C4: Nota
A5: Erro tolerável (= materialidade de execução, R$) | B5: =PT320_Materialidade!C19 -> 38160038
A6: Fator de confiança RF (95%, erro esperado zero - Poisson) | B6: 3
A7: População sujeita a MUS (R$, sem itens-chave nem negativos) | B7: 2.016194e+10 | C7: SINTÉTICO
A8: Intervalo amostral (R$) = erro tolerável / RF | B8: =B5/B6 -> 12720012
A9: Tamanho da amostra calculado = população / intervalo | B9: =ROUNDUP(B7/B8,0) -> 1586
A10: Itens efetivamente selecionados (seleção sistemática, início aleatório, semente = matrícula) | B10: 1570 | C10: Menor que o calculado: itens maiores que o intervalo são atingidos mais de uma vez e contados uma só.
A11: Itens-chave testados a 100% (valor >= erro tolerável) | B11: 4
A12: Itens com saldo negativo testados a 100% | B12: 60
A14: Itens da amostra com exceção | B14: 18
A15: Itens da amostra com distorção monetária quantificada | B15: 10
A16: Distorção encontrada na amostra (R$) | B16: 3040314
A17: Precisão básica (R$) = RF x intervalo | B17: =B6*B8 -> 38160038
A18: Distorção projetada (R$) = soma(taint) x intervalo | B18: 39488929
A19: Limite superior de distorção - Stringer/Poisson (R$) | B19: 1.0053075e+08
A20: Conclusão estatística | B20: =IF(B19>B5,"NÃO ACEITA: limite superior > erro tolerável","ACEITA") -> NÃO ACEITA: limite superior > erro tolerável | C20: Resultado SIMULADO. Em trabalho real: ampliar amostra, solicitar correção e reavaliar risco.
A22: Incrementos Poisson 95% (1º ao 10º erro ordenado por taint)
B23: 1.75 | C23: Detalhe da amostra e das exceções: dados/resultados/amostra_mus_selecionada.csv
B24: 1.55
B25: 1.46
B26: 1.4
B27: 1.36
B28: 1.33
B29: 1.31
B30: 1.29
B31: 1.28
B32: 1.27

Sheet PT540_PCE
A1: PT 540 - Estimativa: provisão para perdas de crédito esperadas (nota 8) - recálculo e sensibilidade
A2: Preparador: matrícula 231004987 | Data: 20/10/2026 | Revisão: ____________ (campo reservado; sem assinatura simulada) | Valores em R$ mil, salvo indicação
A4: Faixa (aluguéis + CDU + cotas condominiais) | B4: A vencer | C4: <=90 dias | D4: 91-180 | E4: 181-360 | F4: >360 | G4: Total
A5: Aluguéis | B5: 314349 | C5: 16492 | D5: 15065 | E5: 19554 | F5: 287585 | G5: =SUM(B5:F5) -> 653045
A6: Taxa de cessão de direito de uso | B6: 3121 | C6: 813 | D6: 450 | E6: 987 | F6: 20273 | G6: =SUM(B6:F6) -> 25644
A7: Cotas condominiais | B7: 15118 | C7: 1413 | D7: 3349 | E7: 10346 | F7: 129457 | G7: =SUM(B7:F7) -> 159683
A8: Total por faixa | B8: =SUM(B5:B7) -> 332588 | C8: =SUM(C5:C7) -> 18718 | D8: =SUM(D5:D7) -> 18864 | E8: =SUM(E5:E7) -> 30887 | F8: =SUM(F5:F7) -> 437315 | G8: =SUM(G5:G7) -> 838372
A9: % de provisão (matriz da nota 8, 31/12/2025) | B9: 0.0378 | C9: 0.3952 | D9: 0.6579 | E9: 0.9101 | F9: 1
A10: PCE esperada por faixa (recálculo) | B10: =B8*B9 -> 12571.826 | C10: =C8*C9 -> 7397.3536 | D10: =D8*D9 -> 12410.626 | E10: =E8*E9 -> 28110.259 | F10: =F8*F9 -> 437315 | G10: =SUM(B10:F10) -> 497805.06
A12: PCE total registrada (balanço/nota 8) | B12: 546430
A13: PCE de prestação de serviços e outros (análise individual) - saldo bruto serviços+outros | B13: =73905+22999 -> 96904
A14: Diferença: registrada - recalculada pela matriz | B14: =B12-G10 -> 48624.936
A15: Diferença / saldo bruto de serviços e outros | B15: =B14/B13 -> 0.50178461 | C15: A diferença deve ser explicada pela análise individual (PLANEJADO: exige acesso à análise interna).
A16: Diferença vs materialidade de execução | B16: =B14/PT320_Materialidade!D11 -> 1.2742371
A18: Sensibilidade (pontos percentuais nas faixas vencidas) | B18: -10 p.p. | C18: -5 p.p. | D18: Base | E18: +5 p.p. | F18: +10 p.p.
A19: PCE recalculada (R$ mil) | B19: =B8*B9+C8*MIN(1,C9+(-0.1))+D8*MIN(1,D9+(-0.1))+E8*MIN(1,E9+(-0.1))+F8*F9 -> 490958.16 | C19: =B8*B9+C8*MIN(1,C9+(-0.05))+D8*MIN(1,D9+(-0.05))+E8*MIN(1,E9+(-0.05))+F8*F9 -> 494381.61 | D19: =B8*B9+C8*MIN(1,C9+(0))+D8*MIN(1,D9+(0))+E8*MIN(1,E9+(0))+F8*F9 -> 497805.06 | E19: =B8*B9+C8*MIN(1,C9+(0.05))+D8*MIN(1,D9+(0.05))+E8*MIN(1,E9+(0.05))+F8*F9 -> 501228.51 | F19: =B8*B9+C8*MIN(1,C9+(0.1))+D8*MIN(1,D9+(0.1))+E8*MIN(1,E9+(0.1))+F8*F9 -> 504340.01
A20: Variação vs base (R$ mil) | B20: =B19-$D$19 -> -6846.9 | C20: =C19-$D$19 -> -3423.45 | D20: =D19-$D$19 -> 0 | E20: =E19-$D$19 -> 3423.45 | F20: =F19-$D$19 -> 6534.9413
A21: Variação vs materialidade de execução (x) | B21: =ABS(B20)/PT320_Materialidade!$D$11 -> 0.17942592 | C21: =ABS(C20)/PT320_Materialidade!$D$11 -> 0.089712962 | D21: =ABS(D20)/PT320_Materialidade!$D$11 -> 0 | E21: =ABS(E20)/PT320_Materialidade!$D$11 -> 0.089712962 | F21: =ABS(F20)/PT320_Materialidade!$D$11 -> 0.17125091

Sheet PT520_Analiticos
A1: PT 520 - Procedimentos analíticos (DFP 2025 x 2024, consolidado) - REALIZADO COM EVIDÊNCIA PÚBLICA
A2: Preparador: matrícula 231004987 | Data: 20/10/2026 | Revisão: ____________ (campo reservado; sem assinatura simulada) | Valores em R$ mil, salvo indicação
A3: Premissa didática de reajuste (inflação contratual proxy): | D3: 0.04 | E3: SUBSTITUIR pelo IPCA/IGP-M oficial do período; 4% é premissa do aluno, não dado público.
A4: Conta (R$ mil) | B4: 2025 | C4: 2024 | D4: Var. R$ | E4: Var. % | F4: Expectativa 2025 | G4: Dif. real x esperada | H4: Investigar? | I4: Fonte / premissa
A5: Receitas de aluguéis | B5: 2055493 | C5: 1973209 | D5: =B5-C5 -> 82284 | E5: =IF(C5=0,0,D5/ABS(C5)) -> 0.0417006 | F5: =C5*(1+$D$3) -> 2052137.4 | G5: =B5-F5 -> 3355.64 | H5: =IF(ABS(G5)>PT320_Materialidade!$D$11,"SIM","não") -> não | I5: nota 18
A6: Estacionamento | B6: 634500 | C6: 598008 | D6: =B6-C6 -> 36492 | E6: =IF(C6=0,0,D6/ABS(C6)) -> 0.061022595 | F6: =C6*(1+$D$3) -> 621928.32 | G6: =B6-F6 -> 12571.68 | H6: =IF(ABS(G6)>PT320_Materialidade!$D$11,"SIM","não") -> não | I6: nota 18
A7: Receita de serviços | B7: 341541 | C7: 329946 | D7: =B7-C7 -> 11595 | E7: =IF(C7=0,0,D7/ABS(C7)) -> 0.035142114 | F7: =C7*(1+$D$3) -> 343143.84 | G7: =B7-F7 -> -1602.84 | H7: =IF(ABS(G7)>PT320_Materialidade!$D$11,"SIM","não") -> não | I7: nota 18
A8: Receita líquida total | B8: 2859106 | C8: 2739848 | D8: =B8-C8 -> 119258 | E8: =IF(C8=0,0,D8/ABS(C8)) -> 0.043527232 | F8: =C8*(1+$D$3) -> 2849441.9 | G8: =B8-F8 -> 9664.08 | H8: =IF(ABS(G8)>PT320_Materialidade!$D$11,"SIM","não") -> não | I8: DRE
A9: Custo de aluguéis e serviços | B9: 746938 | C9: 718981 | D9: =B9-C9 -> 27957 | E9: =IF(C9=0,0,D9/ABS(C9)) -> 0.038884199 | F9: =C9*(1+$D$3) -> 747740.24 | G9: =B9-F9 -> -802.24 | H9: =IF(ABS(G9)>PT320_Materialidade!$D$11,"SIM","não") -> não | I9: DRE/nota 19
A10: Depreciação e amortização de propriedades (custo) | B10: 459233 | C10: 451396 | D10: =B10-C10 -> 7837 | E10: =IF(C10=0,0,D10/ABS(C10)) -> 0.017361696 | H10: =IF(ABS(D10)>PT320_Materialidade!$D$11,"SIM","não") -> não | I10: nota 19
A11: Despesas com vendas, gerais e administrativas | B11: 692505 | C11: 704220 | D11: =B11-C11 -> -11715 | E11: =IF(C11=0,0,D11/ABS(C11)) -> -0.016635426 | F11: =C11*(1+$D$3) -> 732388.8 | G11: =B11-F11 -> -39883.8 | H11: =IF(ABS(G11)>PT320_Materialidade!$D$11,"SIM","não") -> SIM | I11: nota 20
A12: Resultado financeiro líquido | B12: -521759 | C12: -584923 | D12: =B12-C12 -> 63164 | E12: =IF(C12=0,0,D12/ABS(C12)) -> 0.10798686 | H12: =IF(ABS(D12)>PT320_Materialidade!$D$11,"SIM","não") -> SIM | I12: DRE/nota 21
A13: Lucro antes dos impostos (LAIR) | B13: 1017601 | C13: 868181 | D13: =B13-C13 -> 149420 | E13: =IF(C13=0,0,D13/ABS(C13)) -> 0.17210697 | H13: =IF(ABS(D13)>PT320_Materialidade!$D$11,"SIM","não") -> SIM | I13: DRE
A14: Contas a receber líquido (circ.+não circ.) | B14: 554236 | C14: 585193 | D14: =B14-C14 -> -30957 | E14: =IF(C14=0,0,D14/ABS(C14)) -> -0.052900496 | H14: =IF(ABS(D14)>PT320_Materialidade!$D$11,"SIM","não") -> não | I14: nota 8
A15: Provisão p/ perdas de crédito esperadas | B15: 546430 | C15: 519209 | D15: =B15-C15 -> 27221 | E15: =IF(C15=0,0,D15/ABS(C15)) -> 0.052427828 | H15: =IF(ABS(D15)>PT320_Materialidade!$D$11,"SIM","não") -> não | I15: nota 8
A16: Propriedades para investimento | B16: 20381666 | C16: 20700140 | D16: =B16-C16 -> -318474 | E16: =IF(C16=0,0,D16/ABS(C16)) -> -0.015385113 | H16: =IF(ABS(D16)>PT320_Materialidade!$D$11,"SIM","não") -> SIM | I16: balanço/nota 11
A17: Aplicações financeiras (circ.+não circ.) | B17: 2536587 | C17: 3511385 | D17: =B17-C17 -> -974798 | E17: =IF(C17=0,0,D17/ABS(C17)) -> -0.27761069 | H17: =IF(ABS(D17)>PT320_Materialidade!$D$11,"SIM","não") -> SIM | I17: nota 7
A18: Empréstimos, financiamentos e debêntures | B18: 5879310 | C18: 6645024 | D18: =B18-C18 -> -765714 | E18: =IF(C18=0,0,D18/ABS(C18)) -> -0.11523119 | H18: =IF(ABS(D18)>PT320_Materialidade!$D$11,"SIM","não") -> SIM | I18: nota 13/5
A19: Obrigações por compra e venda de ativos | B19: 17887 | C19: 427236 | D19: =B19-C19 -> -409349 | E19: =IF(C19=0,0,D19/ABS(C19)) -> -0.95813321 | H19: =IF(ABS(D19)>PT320_Materialidade!$D$11,"SIM","não") -> SIM | I19: nota 15.1
A20: Provisão para contingências | B20: 254628 | C20: 241548 | D20: =B20-C20 -> 13080 | E20: =IF(C20=0,0,D20/ABS(C20)) -> 0.054150728 | H20: =IF(ABS(D20)>PT320_Materialidade!$D$11,"SIM","não") -> não | I20: nota 14
A21: Depósitos judiciais | B21: 192477 | C21: 169019 | D21: =B21-C21 -> 23458 | E21: =IF(C21=0,0,D21/ABS(C21)) -> 0.13878913 | H21: =IF(ABS(D21)>PT320_Materialidade!$D$11,"SIM","não") -> não | I21: balanço
A22: Dividendos a pagar | B22: 440839 | C22: 211798 | D22: =B22-C22 -> 229041 | E22: =IF(C22=0,0,D22/ABS(C22)) -> 1.0814125 | H22: =IF(ABS(D22)>PT320_Materialidade!$D$11,"SIM","não") -> SIM | I22: balanço
A24: Limite de investigação = materialidade de execução (R$ mil) | B24: =PT320_Materialidade!D11 -> 38160.037
A25: Obs.: onde não há expectativa independente (linhas sem coluna F), o teste é de variação absoluta contra o limite; 'SIM' exige explicação documentada (PT 520).

Sheet PT570_Continuidade
A1: PT 570 - Continuidade operacional: liquidez e endividamento (DFP 2025, consolidado) - REAL
A2: Preparador: matrícula 231004987 | Data: 20/10/2026 | Revisão: ____________ (campo reservado; sem assinatura simulada) | Valores em R$ mil, salvo indicação
A4: Indicador (R$ mil) | B4: 31/12/2025 | C4: 31/12/2024 | D4: Fonte
A5: Ativo circulante | B5: 3316531 | C5: 4271851 | D5: balanço
A6: Passivo circulante | B6: 1284420 | C6: 2265460 | D6: balanço
A7: Caixa e equivalentes | B7: 60570 | C7: 47771 | D7: balanço
A8: Aplicações financeiras (total) | B8: 2536587 | C8: 3511385 | D8: nota 7
A9: Empréstimos, financiamentos e debêntures (total) | B9: 5879310 | C9: 6645024 | D9: nota 5/13
A10: Obrigações compra e venda de ativos | B10: 17887 | C10: 427236 | D10: nota 5
A11: Derivativos (passivo) | B11: 132740 | C11: 158383 | D11: nota 5
A12: Patrimônio líquido | B12: 13899006 | C12: 14134520 | D12: balanço
A14: Liquidez corrente | B14: =B5/B6 -> 2.5821234 | C14: =C5/C6 -> 1.885644
A15: Dívida líquida (empréstimos + obrigações - caixa - aplicações + derivativos) | B15: =B9+B10-B7-B8+B11 -> 3432780 | C15: =C9+C10-C7-C8+C11 -> 3671487 | D15: Nota 5 divulga 3.432.780 (2025) e 3.671.487 (2024)
A16: Dívida líquida / PL | B16: =B15/B12 -> 0.24698025 | C16: =C15/C12 -> 0.25975321
A17: Diferença para a dívida líquida da nota 5 (2025) | B17: =B15-3432780 -> 0
A18: EBITDA gerencial 2025 (R$ mil) - fonte secundária; usar o oficial | B18: 2076500 | D18: Fato Relevante 10/03/2026 (via acionista.com.br)
A19: Dívida líquida / EBITDA (covenant da nota 13: <= 3,5x, base gerencial ajustada) | B19: =B15/B18 -> 1.6531568 | D19: Aproximação: o covenant usa EBITDA Ajustado Consolidado Gerencial; cálculo contratual = PLANEJADO (exige dados internos).
A20: Folga vs limite 3,5x | B20: =3.5-B19 -> 1.8468432

Sheet PT450_Distorcoes
A1: PT 450 - Mapa de distorções (SIMULADAS na base sintética; nenhuma é achado sobre a Allos real)
A2: Preparador: matrícula 231004987 | Data: 20/10/2026 | Revisão: ____________ (campo reservado; sem assinatura simulada) | Valores em R$ mil, salvo indicação
A4: Tipo (registro de erros inseridos) | B4: Qtd | C4: Distorção potencial (R$) | D4: Efeito no saldo da base (R$) | E4: Corrigida? | F4: Natureza
A5: DUPLICIDADE | B5: 150 | C5: 22927175 | D5: 22927175 | E5: Não (simulação: pendente de ajuste) | F5: Quantitativa - existência
A6: CORTE (ATIVACAO EM 2026) | B6: 120 | C6: 10090343 | D6: 0 | E6: Não (simulação: pendente de ajuste) | F6: Quantitativa - corte
A7: DEPRECIACAO INCORRETA | B7: 200 | C7: 134594.16 | D7: 5410.58 | E7: Não (simulação: pendente de ajuste) | F7: Quantitativa - mensuração
A8: BAIXADO COM SALDO | B8: 80 | C8: 14084610 | D8: 0 | E8: Não (simulação: pendente de ajuste) | F8: Quantitativa - existência/direitos
A9: VCL NEGATIVO | B9: 60 | C9: 18492927 | D9: -18492927 | E9: Não (simulação: pendente de ajuste) | F9: Quantitativa - mensuração
A10: TERRENO DEPRECIADO | B10: 40 | C10: 23071.29 | D10: -23071.29 | E10: Não (simulação: pendente de ajuste) | F10: Quantitativa - classificação
A11: SEM DOCUMENTO SUPORTE | B11: 300 | C11: 43733663 | D11: 0 | E11: Não (simulação: pendente de ajuste) | F11: Controle (potencial)
A12: LANCAMENTO MANUAL ATIPICO | B12: 90 | C12: 64325618 | D12: 62082392 | E12: Não (simulação: pendente de ajuste) | F12: Qualitativa - burla de controles/fraude (NBC TA 240)
A13: TOTAL | B13: =SUM(B5:B12) -> 1040 | C13: =SUM(C5:C12) -> 173812002
A14: Distorções monetárias quantificadas (exclui 'sem documento' e 'manual atípico') | C14: 65752721
A15: Materialidade global (R$) | C15: =PT320_Materialidade!B19 -> 50880050
A16: Quantificada / materialidade global | C16: =C14/C15 -> 1.2923085
A17: Conclusão SIMULADA | C17: =IF(C16>1,"Distorções não corrigidas EXCEDEM a materialidade: opinião modificada, se persistissem","Abaixo da materialidade") -> Distorções não corrigidas EXCEDEM a materialidade: opinião modificada, se persistissem

Sheet Cobertura_Normas
A1: Matriz de cobertura: norma x papel de trabalho (versões em versoes_normas.py e no PDF)
A2: Preparador: matrícula 231004987 | Data: 20/10/2026 | Revisão: ____________ (campo reservado; sem assinatura simulada) | Valores em R$ mil, salvo indicação
A4: Norma (versão consultada, CFC, 20/10/2026) | B4: Papel de trabalho | C4: Natureza da execução predominante
A5: NBC TA Estrutura Conceitual - Estrutura Conceitual para Trabalhos de Asseguração (DOU 25/11/15) | B5: PT EC | C5: Realizado (documental)
A6: NBC TA 200 (R1) (DOU 05/09/16) | B6: PT 200 | C6: Realizado + planejado
A7: NBC TA 210 (R1) (DOU 05/09/16) | B7: PT 210 | C7: Realizado (carta didática)
A8: NBC TA 220 (R3) (DOU 09/12/21) | B8: PT 220 | C8: Planejado
A9: NBC TA 230 (R1) (DOU 05/09/16) | B9: PT 230 | C9: Realizado (estrutura do dossiê)
A10: NBC TA 240 (R1) (DOU 05/09/16) | B10: PT 240 | C10: Realizado + simulado (testes de lançamentos)
A11: NBC TA 250 (DOU 14/02/19) | B11: PT 250 | C11: Realizado (mapeamento) + planejado
A12: NBC TA 260 (R2) (DOU 04/07/16) | B12: PT 260 | C12: Planejado (minuta)
A13: NBC TA 265 (Res. CFC 1.210/09) | B13: PT 265 | C13: Hipóteses x constatações simuladas
A14: NBC TA 300 (R1) (DOU 05/09/16) | B14: PT 300 | C14: Realizado (plano) + cronograma
A15: NBC TA 315 (R2) (DOU 02/09/21) | B15: PT 315 | C15: Realizado com evidência pública
... A31: NBC TA 600 (R2) (DOU 06/12/23) | B31: PT 600 | C31: Realizado (mapa) + planejado
